MANIFEST.in
setup.py
nemo_plokamos_plugin/__init__.py
nemo_plokamos_plugin.egg-info/PKG-INFO
nemo_plokamos_plugin.egg-info/SOURCES.txt
nemo_plokamos_plugin.egg-info/dependency_links.txt
nemo_plokamos_plugin.egg-info/not-zip-safe
nemo_plokamos_plugin.egg-info/requires.txt
nemo_plokamos_plugin.egg-info/top_level.txt
nemo_plokamos_plugin/data/assets/css/annotator.css
nemo_plokamos_plugin/data/assets/img/plokamos-clicked.svg
nemo_plokamos_plugin/data/assets/img/plokamos.svg
nemo_plokamos_plugin/data/assets/img/plokamos_icon.png
nemo_plokamos_plugin/data/assets/js/annotator.js
nemo_plokamos_plugin/data/assets/js/rdfstore.js
nemo_plokamos_plugin/data/assets/json/labels.json
nemo_plokamos_plugin/data/assets/json/namespaces.json
nemo_plokamos_plugin/data/assets/json/sparql-result.json
nemo_plokamos_plugin/data/templates/container.html