Metadata-Version: 1.0
Name: nemo-plokamos-plugin
Version: 0.0.21
Summary: Plugin for Capitains Nemo to load Perseids Plokamos Annotator on passage page
Home-page: https://github.com/perseids-project/nemo_plokamos_plugin
Author: Bridget Almas
Author-email: balmas@gmail.com
License: GNU GPL
Platform: UNKNOWN
